jellypy/__init__.py
jellypy/pyCIPAPI/__init__.py
jellypy/pyCIPAPI/auth.py
jellypy/pyCIPAPI/auth_credentials.py
jellypy/pyCIPAPI/config.py
jellypy/pyCIPAPI/example_auth_credentials.py
jellypy/pyCIPAPI/interpretation_requests.py
jellypy/pyCIPAPI/opencga.py
jellypy/pyCIPAPI/summary_findings.py
jellypy_pyCIPAPI-0.2.3.dist-info/METADATA
jellypy_pyCIPAPI-0.2.3.dist-info/WHEEL
jellypy_pyCIPAPI-0.2.3.dist-info/top_level.txt
jellypy_pyCIPAPI-0.2.3.dist-info/RECORD
